blockchainetl/__init__.py
blockchainetl/atomic_counter.py
blockchainetl/csv_utils.py
blockchainetl/exporters.py
blockchainetl/file_utils.py
blockchainetl/logging_utils.py
blockchainetl/jobs/__init__.py
blockchainetl/jobs/base_job.py
blockchainetl/jobs/exporters/__init__.py
blockchainetl/jobs/exporters/composite_item_exporter.py
blockchainetl/jobs/exporters/console_item_exporter.py
blockchainetl/jobs/exporters/google_pubsub_item_exporter.py
blockchainetl/jobs/exporters/in_memory_item_exporter.py
blockchainetl/jobs/exporters/postgres_item_exporter.py
blockchainetl/streaming/__init__.py
blockchainetl/streaming/postgres_utils.py
blockchainetl/streaming/streamer.py
blockchainetl/streaming/streamer_adapter_stub.py
blockchainetl/streaming/streaming_utils.py
celoetl/__init__.py
celoetl/__main__.py
celoetl/atomic_counter.py
celoetl/csv_utils.py
celoetl/erc20_abi.py
celoetl/exporters.py
celoetl/json_rpc_requests.py
celoetl/mainnet_daofork_state_changes.py
celoetl/mainnet_genesis_alloc.py
celoetl/misc_utils.py
celoetl/progress_logger.py
celoetl/thread_local_proxy.py
celoetl/utils.py
celoetl/cli/__init__.py
celoetl/cli/export_all.py
celoetl/cli/export_blocks_and_transactions.py
celoetl/cli/export_contracts.py
celoetl/cli/export_geth_traces.py
celoetl/cli/export_receipts_and_logs.py
celoetl/cli/export_token_transfers.py
celoetl/cli/export_tokens.py
celoetl/cli/export_traces.py
celoetl/cli/extract_contracts.py
celoetl/cli/extract_csv_column.py
celoetl/cli/extract_field.py
celoetl/cli/extract_geth_traces.py
celoetl/cli/extract_token_transfers.py
celoetl/cli/extract_tokens.py
celoetl/cli/filter_items.py
celoetl/cli/get_block_range_for_date.py
celoetl/cli/get_block_range_for_timestamps.py
celoetl/cli/get_keccak_hash.py
celoetl/cli/stream.py
celoetl/domain/__init__.py
celoetl/domain/block.py
celoetl/domain/contract.py
celoetl/domain/geth_trace.py
celoetl/domain/receipt.py
celoetl/domain/receipt_log.py
celoetl/domain/token.py
celoetl/domain/token_transfer.py
celoetl/domain/trace.py
celo_etl-0.0.2.dist-info/LICENSE
celo_etl-0.0.2.dist-info/METADATA
celo_etl-0.0.2.dist-info/WHEEL
celo_etl-0.0.2.dist-info/entry_points.txt
celo_etl-0.0.2.dist-info/top_level.txt
celo_etl-0.0.2.dist-info/RECORD
