Metadata-Version: 2.1
Name: celo-etl
Version: 0.0.2
Summary: Tools for exporting Celo blockchain data to CSV or JSON
Home-page: https://github.com/codabl/celo-etl
Author: Gonzalo Astorga
Author-email: gonzalo@codabl.com
License: UNKNOWN
Project-URL: Bug Reports, https://github.com/codabl/celo-etl/issues
Project-URL: Source, https://github.com/codabl/celo-etl
Keywords: celo
Platform: UNKNOWN
Classifier: Development Status :: 5 - Production/Stable
Classifier: Intended Audience :: Developers
Classifier: License :: OSI Approved :: MIT License
Classifier: Programming Language :: Python :: 3
Classifier: Programming Language :: Python :: 3.5
Classifier: Programming Language :: Python :: 3.6
Classifier: Programming Language :: Python :: 3.7
Requires-Python: >=3.5.3,<3.8.0
Requires-Dist: web3 (==4.7.2)
Requires-Dist: eth-utils (==1.8.4)
Requires-Dist: eth-abi (==1.3.0)
Requires-Dist: python-dateutil (==2.7.0)
Requires-Dist: click (==7.0)
Requires-Dist: ethereum-dasm (==0.1.4)
Provides-Extra: dev
Requires-Dist: pytest (~=4.3.0) ; extra == 'dev'
Provides-Extra: streaming
Requires-Dist: timeout-decorator (==0.4.1) ; extra == 'streaming'
Requires-Dist: google-cloud-pubsub (==0.39.1) ; extra == 'streaming'
Requires-Dist: sqlalchemy (==1.3.13) ; extra == 'streaming'
Requires-Dist: pg8000 (==1.13.2) ; extra == 'streaming'
